byted_mysql_python/__init__.py
byted_mysql_python-0.0.1.dist-info/METADATA
byted_mysql_python-0.0.1.dist-info/WHEEL
byted_mysql_python-0.0.1.dist-info/top_level.txt
byted_mysql_python-0.0.1.dist-info/RECORD
